Metadata-Version: 1.1
Name: Flask-SimpleACL
Version: 1.2
Summary: Simple ACL extension
Home-page: UNKNOWN
Author: swerwer
Author-email: UNKNOWN
License: BSD
Platform: any
Classifier: Environment :: Web Environment
Classifier: Intended Audience :: Developers
Classifier: License :: OSI Approved :: BSD License
Classifier: Operating System :: OS Independent
Classifier: Programming Language :: Python
